[{"place_id":66066225,"licence":"Data © OpenStreetMap contributors, ODbL 1.0. http://osm.org/copyright","osm_type":"node","osm_id":263359996,"lat":"45.8155828","lon":"14.3796888","category":"place","type":"village","place_rank":19,"importance":0.3759772939504354,"addresstype":"village","name":"Begunje pri Cerknici","display_name":"Begunje pri Cerknici, Cerknica, 1382, Slovenia","address":{"village":"Begunje pri Cerknici","town":"Cerknica","ISO3166-2-lvl8":"SI-013","postcode":"1382","country":"Slovenia","country_code":"si"},"boundingbox":["45.7955828","45.8355828","14.3596888","14.3996888"]},{"place_id":66888987,"licence":"Data © OpenStreetMap contributors, ODbL 1.0. http://osm.org/copyright","osm_type":"way","osm_id":297039829,"lat":"45.821697","lon":"14.379001465426022","category":"landuse","type":"industrial","place_rank":22,"importance":0.2000099999999999,"addresstype":"industrial","name":"Begunje pri Cerknici","display_name":"Begunje pri Cerknici, Cerknica, 1382, Slovenia","address":{"industrial":"Begunje pri Cerknici","village":"Begunje pri Cerknici","town":"Cerknica","ISO3166-2-lvl8":"SI-013","postcode":"1382","country":"Slovenia","country_code":"si"},"boundingbox":["45.8208203","45.8225720","14.3774847","14.3804016"]}]