[{"place_id":326951814,"licence":"Data © OpenStreetMap contributors, ODbL 1.0. http://osm.org/copyright","osm_type":"relation","osm_id":7508928,"lat":"36.9336934","lon":"-82.6298965","category":"boundary","type":"administrative","place_rank":12,"importance":0.4687999053882964,"addresstype":"city","name":"Norton","display_name":"Norton, Virginia, 24273, United States","address":{"city":"Norton","state":"Virginia","ISO3166-2-lvl4":"US-VA","postcode":"24273","country":"United States","country_code":"us"},"boundingbox":["36.9001165","36.9597637","-82.6636261","-82.5891900"]}]