[{"place_id":44227085,"licence":"Data © OpenStreetMap contributors, ODbL 1.0. http://osm.org/copyright","osm_type":"relation","osm_id":332818,"lat":"-2.5907563","lon":"-45.3623652","category":"boundary","type":"administrative","place_rank":16,"importance":0.40995233416786564,"addresstype":"municipality","name":"Presidente Sarney","display_name":"Presidente Sarney, Região Geográfica Imediata de Pinheiro, Região Geográfica Intermediária de São Luís, Maranhão, Northeast Region, 65204-000, Brazil","address":{"municipality":"Presidente Sarney","state_district":"Região Geográfica Intermediária de São Luís","state":"Maranhão","ISO3166-2-lvl4":"BR-MA","region":"Northeast Region","postcode":"65204-000","country":"Brazil","country_code":"br"},"boundingbox":["-2.7710000","-2.4110000","-45.4920000","-45.2420000"]}]