[{"place_id":159094549,"licence":"Data © OpenStreetMap contributors, ODbL 1.0. http://osm.org/copyright","osm_type":"node","osm_id":31518956,"lat":"53.9988786","lon":"22.318426","category":"place","type":"village","place_rank":19,"importance":0.325302870611459,"addresstype":"village","name":"Świętajno","display_name":"Świętajno, gmina Świętajno, Olecko County, Warmian-Masurian Voivodeship, 19-411, Poland","address":{"village":"Świętajno","municipality":"gmina Świętajno","county":"Olecko County","state":"Warmian-Masurian Voivodeship","ISO3166-2-lvl4":"PL-28","postcode":"19-411","country":"Poland","country_code":"pl"},"boundingbox":["53.9788786","54.0188786","22.2984260","22.3384260"]},{"place_id":157452673,"licence":"Data © OpenStreetMap contributors, ODbL 1.0. http://osm.org/copyright","osm_type":"node","osm_id":692618273,"lat":"53.5653707","lon":"21.2179549","category":"place","type":"village","place_rank":19,"importance":0.3075723342298069,"addresstype":"village","name":"Świętajno","display_name":"Świętajno, gmina Świętajno, Szczytno County, Warmian-Masurian Voivodeship, 12-140, Poland","address":{"village":"Świętajno","municipality":"gmina Świętajno","county":"Szczytno County","state":"Warmian-Masurian Voivodeship","ISO3166-2-lvl4":"PL-28","postcode":"12-140","country":"Poland","country_code":"pl"},"boundingbox":["53.5453707","53.5853707","21.1979549","21.2379549"]},{"place_id":158223600,"licence":"Data © OpenStreetMap contributors, ODbL 1.0. http://osm.org/copyright","osm_type":"way","osm_id":170392945,"lat":"53.7934257","lon":"20.686982637094808","category":"natural","type":"water","place_rank":22,"importance":0.2000099999999999,"addresstype":"water","name":"Świętajno","display_name":"Świętajno, Sapuny, gmina Barczewo, Olsztyn County, Warmian-Masurian Voivodeship, 11-010, Poland","address":{"water":"Świętajno","village":"Sapuny","municipality":"gmina Barczewo","county":"Olsztyn County","state":"Warmian-Masurian Voivodeship","ISO3166-2-lvl4":"PL-28","postcode":"11-010","country":"Poland","country_code":"pl"},"boundingbox":["53.7907891","53.7964472","20.6827912","20.6897875"]},{"place_id":154437037,"licence":"Data © OpenStreetMap contributors, ODbL 1.0. http://osm.org/copyright","osm_type":"relation","osm_id":5399962,"lat":"54.002509599999996","lon":"22.310654128588588","category":"natural","type":"water","place_rank":22,"importance":0.2000099999999999,"addresstype":"water","name":"Świętajno","display_name":"Świętajno, Sulejki, gmina Świętajno, Olecko County, Warmian-Masurian Voivodeship, 19-411, Poland","address":{"water":"Świętajno","village":"Sulejki","municipality":"gmina Świętajno","county":"Olecko County","state":"Warmian-Masurian Voivodeship","ISO3166-2-lvl4":"PL-28","postcode":"19-411","country":"Poland","country_code":"pl"},"boundingbox":["53.9956532","54.0095292","22.3039197","22.3221291"]},{"place_id":159169553,"licence":"Data © OpenStreetMap contributors, ODbL 1.0. http://osm.org/copyright","osm_type":"node","osm_id":692618275,"lat":"53.6032625","lon":"21.2517858","category":"place","type":"locality","place_rank":25,"importance":0.12500999999999995,"addresstype":"locality","name":"Świętajno","display_name":"Świętajno, Łączyk, Kobiel, gmina Świętajno, Szczytno County, Warmian-Masurian Voivodeship, 12-140, Poland","address":{"locality":"Świętajno","hamlet":"Łączyk","village":"Kobiel","municipality":"gmina Świętajno","county":"Szczytno County","state":"Warmian-Masurian Voivodeship","ISO3166-2-lvl4":"PL-28","postcode":"12-140","country":"Poland","country_code":"pl"},"boundingbox":["53.5932625","53.6132625","21.2417858","21.2617858"]},{"place_id":159486346,"licence":"Data © OpenStreetMap contributors, ODbL 1.0. http://osm.org/copyright","osm_type":"relation","osm_id":2991548,"lat":"53.58926135","lon":"21.269910110905727","category":"boundary","type":"administrative","place_rank":14,"importance":0.37443815291409516,"addresstype":"municipality","name":"gmina Świętajno","display_name":"gmina Świętajno, Szczytno County, Warmian-Masurian Voivodeship, Poland","address":{"municipality":"gmina Świętajno","county":"Szczytno County","state":"Warmian-Masurian Voivodeship","ISO3166-2-lvl4":"PL-28","country":"Poland","country_code":"pl"},"boundingbox":["53.4744225","53.7042342","21.1099410","21.4436446"]},{"place_id":155138793,"licence":"Data © OpenStreetMap contributors, ODbL 1.0. http://osm.org/copyright","osm_type":"relation","osm_id":2983056,"lat":"54.0232783","lon":"22.26579309594846","category":"boundary","type":"administrative","place_rank":14,"importance":0.3721284718961503,"addresstype":"municipality","name":"gmina Świętajno","display_name":"gmina Świętajno, Olecko County, Warmian-Masurian Voivodeship, 19-411, Poland","address":{"municipality":"gmina Świętajno","county":"Olecko County","state":"Warmian-Masurian Voivodeship","ISO3166-2-lvl4":"PL-28","postcode":"19-411","country":"Poland","country_code":"pl"},"boundingbox":["53.9288055","54.1165851","22.1497398","22.4461147"]},{"place_id":159610715,"licence":"Data © OpenStreetMap contributors, ODbL 1.0. http://osm.org/copyright","osm_type":"node","osm_id":692618272,"lat":"53.5795463","lon":"21.2302049","category":"place","type":"hamlet","place_rank":20,"importance":0.25000999999999995,"addresstype":"hamlet","name":"Świętajno-Kolonia","display_name":"Świętajno-Kolonia, gmina Świętajno, Szczytno County, Warmian-Masurian Voivodeship, 12-140, Poland","address":{"hamlet":"Świętajno-Kolonia","municipality":"gmina Świętajno","county":"Szczytno County","state":"Warmian-Masurian Voivodeship","ISO3166-2-lvl4":"PL-28","postcode":"12-140","country":"Poland","country_code":"pl"},"boundingbox":["53.5595463","53.5995463","21.2102049","21.2502049"]}]