[{"place_id":270196472,"licence":"Data © OpenStreetMap contributors, ODbL 1.0. http://osm.org/copyright","osm_type":"node","osm_id":96121833,"lat":"55.8353762","lon":"-4.0887028","category":"place","type":"village","place_rank":19,"importance":0.31279513946526605,"addresstype":"village","name":"Birkenshaw","display_name":"Birkenshaw, North Lanarkshire, Scotland, G71 6BB, United Kingdom","address":{"village":"Birkenshaw","county":"North Lanarkshire","ISO3166-2-lvl6":"GB-NLK","state":"Scotland","ISO3166-2-lvl4":"GB-SCT","postcode":"G71 6BB","country":"United Kingdom","country_code":"gb"},"boundingbox":["55.8153762","55.8553762","-4.1087028","-4.0687028"]},{"place_id":271434026,"licence":"Data © OpenStreetMap contributors, ODbL 1.0. http://osm.org/copyright","osm_type":"node","osm_id":59005633,"lat":"53.7496595","lon":"-1.6951239","category":"place","type":"village","place_rank":19,"importance":0.27501,"addresstype":"village","name":"Birkenshaw","display_name":"Birkenshaw, Kirklees, West Yorkshire, England, BD11 2EF, United Kingdom","address":{"village":"Birkenshaw","city":"Kirklees","ISO3166-2-lvl8":"GB-KIR","state_district":"West Yorkshire","state":"England","ISO3166-2-lvl4":"GB-ENG","postcode":"BD11 2EF","country":"United Kingdom","country_code":"gb"},"boundingbox":["53.7296595","53.7696595","-1.7151239","-1.6751239"]},{"place_id":268737029,"licence":"Data © OpenStreetMap contributors, ODbL 1.0. http://osm.org/copyright","osm_type":"way","osm_id":974113657,"lat":"55.905958850000005","lon":"-3.7052146063996174","category":"landuse","type":"farmyard","place_rank":22,"importance":0.2000099999999999,"addresstype":"farmyard","name":"Birkenshaw","display_name":"Birkenshaw, Armadale, West Lothian, Scotland, United Kingdom","address":{"farmyard":"Birkenshaw","town":"Armadale","county":"West Lothian","ISO3166-2-lvl6":"GB-WLN","state":"Scotland","ISO3166-2-lvl4":"GB-SCT","country":"United Kingdom","country_code":"gb"},"boundingbox":["55.9050487","55.9070418","-3.7070398","-3.7043177"]}]