[{"place_id":3564957,"licence":"Data © OpenStreetMap contributors, ODbL 1.0. http://osm.org/copyright","osm_type":"node","osm_id":158655783,"lat":"37.4966375","lon":"-78.2446058","category":"place","type":"village","place_rank":19,"importance":0.3224057754348258,"addresstype":"village","name":"Cumberland","display_name":"Cumberland, Cumberland County, Virginia, 23040, United States","address":{"village":"Cumberland","county":"Cumberland County","state":"Virginia","ISO3166-2-lvl4":"US-VA","postcode":"23040","country":"United States","country_code":"us"},"boundingbox":["37.4766375","37.5166375","-78.2646058","-78.2246058"]}]