[{"place_id":282901501,"licence":"Data © OpenStreetMap contributors, ODbL 1.0. http://osm.org/copyright","osm_type":"relation","osm_id":11852087,"lat":"42.7679787","lon":"-1.2500869","category":"waterway","type":"river","place_rank":18,"importance":0.30000999999999994,"addresstype":"river","name":"Areta","display_name":"Areta, Urraúl Alto, Pirinioaurrea / Prepirineo, Spain","address":{"river":"Areta","city":"Urraúl Alto","county":"Pirinioaurrea / Prepirineo","country":"Spain","country_code":"es"},"boundingbox":["42.6800258","42.8473959","-1.3101197","-1.1835187"]},{"place_id":284405591,"licence":"Data © OpenStreetMap contributors, ODbL 1.0. http://osm.org/copyright","osm_type":"relation","osm_id":10041456,"lat":"43.1470637","lon":"-2.9429016","category":"place","type":"suburb","place_rank":19,"importance":0.27501,"addresstype":"suburb","name":"Areta","display_name":"Areta, Laudio/Llodio, Aiarako kuadrilla/Cuadrilla de Ayala, Álava, Autonomous Community of the Basque Country, 01400, Spain","address":{"suburb":"Areta","municipality":"Laudio/Llodio","village":"Aiarako kuadrilla/Cuadrilla de Ayala","province":"Álava","ISO3166-2-lvl6":"ES-VI","state":"Autonomous Community of the Basque Country","ISO3166-2-lvl4":"ES-PV","postcode":"01400","country":"Spain","country_code":"es"},"boundingbox":["43.1357404","43.1572290","-2.9576701","-2.9354569"]},{"place_id":282932744,"licence":"Data © OpenStreetMap contributors, ODbL 1.0. http://osm.org/copyright","osm_type":"node","osm_id":7529995959,"lat":"43.175436","lon":"-2.4570347","category":"place","type":"quarter","place_rank":20,"importance":0.25000999999999995,"addresstype":"quarter","name":"Areta","display_name":"Areta, Otaola-Kiñarra, Eibar, Debabarrena, Gipuzkoa, Autonomous Community of the Basque Country, 20600, Spain","address":{"quarter":"Areta","suburb":"Otaola-Kiñarra","town":"Eibar","county":"Debabarrena","province":"Gipuzkoa","ISO3166-2-lvl6":"ES-SS","state":"Autonomous Community of the Basque Country","ISO3166-2-lvl4":"ES-PV","postcode":"20600","country":"Spain","country_code":"es"},"boundingbox":["43.1654360","43.1854360","-2.4670347","-2.4470347"]},{"place_id":283959854,"licence":"Data © OpenStreetMap contributors, ODbL 1.0. http://osm.org/copyright","osm_type":"node","osm_id":1241759051,"lat":"42.8222066","lon":"-2.4111613","category":"place","type":"locality","place_rank":25,"importance":0.12500999999999995,"addresstype":"locality","name":"Areta","display_name":"Areta, Alaitza, Iruraiz-Gauna, Arabako lautada/Llanada Alavesa, Álava, Autonomous Community of the Basque Country, 01207, Spain","address":{"locality":"Areta","hamlet":"Alaitza","city_district":"Alaitza","municipality":"Iruraiz-Gauna","county":"Arabako lautada/Llanada Alavesa","province":"Álava","ISO3166-2-lvl6":"ES-VI","state":"Autonomous Community of the Basque Country","ISO3166-2-lvl4":"ES-PV","postcode":"01207","country":"Spain","country_code":"es"},"boundingbox":["42.8122066","42.8322066","-2.4211613","-2.4011613"]},{"place_id":283286787,"licence":"Data © OpenStreetMap contributors, ODbL 1.0. http://osm.org/copyright","osm_type":"node","osm_id":8547043426,"lat":"43.0813197","lon":"-1.8062848","category":"place","type":"locality","place_rank":25,"importance":0.12500999999999995,"addresstype":"locality","name":"Areta","display_name":"Areta, Eratsun, Baztan-Bidasoa, Spain","address":{"locality":"Areta","village":"Eratsun","county":"Baztan-Bidasoa","country":"Spain","country_code":"es"},"boundingbox":["43.0713197","43.0913197","-1.8162848","-1.7962848"]}]