[{"place_id":75080543,"licence":"Data © OpenStreetMap contributors, ODbL 1.0. http://osm.org/copyright","osm_type":"relation","osm_id":43058,"lat":"44.3770311","lon":"7.911036","category":"boundary","type":"administrative","place_rank":16,"importance":0.5420368234246278,"addresstype":"village","name":"San Michele Mondovì","display_name":"San Michele Mondovì, Cuneo, Piedmont, Italy","address":{"village":"San Michele Mondovì","county":"Cuneo","ISO3166-2-lvl6":"IT-CN","state":"Piedmont","ISO3166-2-lvl4":"IT-21","country":"Italy","country_code":"it"},"boundingbox":["44.3392802","44.4004132","7.8934505","7.9483892"]}]