[{"place_id":21575358,"licence":"Data © OpenStreetMap contributors, ODbL 1.0. http://osm.org/copyright","osm_type":"relation","osm_id":7785081,"lat":"45.0483404","lon":"-73.58562753582805","category":"boundary","type":"administrative","place_rank":16,"importance":0.3230614454416833,"addresstype":"city","name":"Hemmingford (village)","display_name":"Hemmingford (village), Les Jardins-de-Napierville, Montérégie, Quebec, J0L 1H0, Canada","address":{"city":"Hemmingford (village)","county":"Les Jardins-de-Napierville","region":"Montérégie","state":"Quebec","ISO3166-2-lvl4":"CA-QC","postcode":"J0L 1H0","country":"Canada","country_code":"ca"},"boundingbox":["45.0429585","45.0545801","-73.5923586","-73.5786469"]},{"place_id":21565000,"licence":"Data © OpenStreetMap contributors, ODbL 1.0. http://osm.org/copyright","osm_type":"relation","osm_id":7785082,"lat":"45.06861859999999","lon":"-73.60169565254733","category":"boundary","type":"administrative","place_rank":16,"importance":0.3139400466797944,"addresstype":"city","name":"Hemmingford (canton)","display_name":"Hemmingford (canton), Les Jardins-de-Napierville, Montérégie, Quebec, J0L 1H8, Canada","address":{"city":"Hemmingford (canton)","county":"Les Jardins-de-Napierville","region":"Montérégie","state":"Quebec","ISO3166-2-lvl4":"CA-QC","postcode":"J0L 1H8","country":"Canada","country_code":"ca"},"boundingbox":["45.0028786","45.1334096","-73.6944775","-73.5107972"]},{"place_id":21586121,"licence":"Data © OpenStreetMap contributors, ODbL 1.0. http://osm.org/copyright","osm_type":"node","osm_id":4756144938,"lat":"45.0474377","lon":"-73.5863187","category":"place","type":"village","place_rank":19,"importance":0.27501,"addresstype":"village","name":"Hemmingford","display_name":"Hemmingford, Hemmingford (village), Les Jardins-de-Napierville, Montérégie, Quebec, J0L 1H0, Canada","address":{"village":"Hemmingford","city":"Hemmingford (village)","county":"Les Jardins-de-Napierville","region":"Montérégie","state":"Quebec","ISO3166-2-lvl4":"CA-QC","postcode":"J0L 1H0","country":"Canada","country_code":"ca"},"boundingbox":["45.0274377","45.0674377","-73.6063187","-73.5663187"]}]