[{"place_id":155881061,"licence":"Data © OpenStreetMap contributors, ODbL 1.0. http://osm.org/copyright","osm_type":"relation","osm_id":2012319,"lat":"52.9265122","lon":"8.642875","category":"boundary","type":"administrative","place_rank":16,"importance":0.35570776425552836,"addresstype":"village","name":"Dünsen","display_name":"Dünsen, Samtgemeinde Harpstedt, Landkreis Oldenburg, Lower Saxony, Germany","address":{"village":"Dünsen","municipality":"Samtgemeinde Harpstedt","county":"Landkreis Oldenburg","state":"Lower Saxony","ISO3166-2-lvl4":"DE-NI","country":"Germany","country_code":"de"},"boundingbox":["52.8925376","52.9435221","8.6051956","8.6565583"]}]