[{"place_id":257346113,"licence":"Data © OpenStreetMap contributors, ODbL 1.0. http://osm.org/copyright","osm_type":"relation","osm_id":1901726,"lat":"39.2841602","lon":"-5.6989098","category":"boundary","type":"administrative","place_rank":16,"importance":0.5040518366738369,"addresstype":"village","name":"Zorita","display_name":"Zorita, Cáceres, Extremadura, 10130, Spain","address":{"village":"Zorita","province":"Cáceres","ISO3166-2-lvl6":"ES-CC","state":"Extremadura","ISO3166-2-lvl4":"ES-EX","postcode":"10130","country":"Spain","country_code":"es"},"boundingbox":["39.1732031","39.3693111","-5.7780052","-5.5588817"]}]