[{"place_id":116394723,"licence":"Data © OpenStreetMap contributors, ODbL 1.0. http://osm.org/copyright","osm_type":"relation","osm_id":440640,"lat":"50.3555088","lon":"15.9185723","category":"boundary","type":"administrative","place_rank":16,"importance":0.46737373995826753,"addresstype":"town","name":"Jaroměř","display_name":"Jaroměř, okres Náchod, Královéhradecký kraj, Northeast, Czechia","address":{"town":"Jaroměř","municipality":"okres Náchod","ISO3166-2-lvl7":"CZ-523","county":"Královéhradecký kraj","ISO3166-2-lvl6":"CZ-52","state":"Northeast","country":"Czechia","country_code":"cz"},"boundingbox":["50.3183115","50.3844282","15.8655562","15.9848754"]},{"place_id":116624441,"licence":"Data © OpenStreetMap contributors, ODbL 1.0. http://osm.org/copyright","osm_type":"relation","osm_id":430361,"lat":"50.35938435","lon":"15.91844817367535","category":"boundary","type":"administrative","place_rank":20,"importance":0.25000999999999995,"addresstype":"suburb","name":"Jaroměř","display_name":"Jaroměř, okres Náchod, Královéhradecký kraj, Northeast, 551 01, Czechia","address":{"suburb":"Jaroměř","town":"Jaroměř","municipality":"okres Náchod","ISO3166-2-lvl7":"CZ-523","county":"Královéhradecký kraj","ISO3166-2-lvl6":"CZ-52","state":"Northeast","postcode":"551 01","country":"Czechia","country_code":"cz"},"boundingbox":["50.3345220","50.3844282","15.8795303","15.9529036"]}]