[{"place_id":237732314,"licence":"Data © OpenStreetMap contributors, ODbL 1.0. http://osm.org/copyright","osm_type":"node","osm_id":29621830,"lat":"56.3061659","lon":"-3.1557626","category":"place","type":"village","place_rank":19,"importance":0.3179649565859212,"addresstype":"village","name":"Collessie","display_name":"Collessie, Fife, Scotland, KY15 7RQ, United Kingdom","address":{"village":"Collessie","county":"Fife","ISO3166-2-lvl6":"GB-FIF","state":"Scotland","ISO3166-2-lvl4":"GB-SCT","postcode":"KY15 7RQ","country":"United Kingdom","country_code":"gb"},"boundingbox":["56.2861659","56.3261659","-3.1757626","-3.1357626"]}]