[{"place_id":266642068,"licence":"Data © OpenStreetMap contributors, ODbL 1.0. http://osm.org/copyright","osm_type":"relation","osm_id":358768,"lat":"34.503879","lon":"135.549966","category":"boundary","type":"administrative","place_rank":14,"importance":0.4446472173275141,"addresstype":"city","name":"Osakasayama","display_name":"Osakasayama, Osaka Prefecture, Japan","address":{"city":"Osakasayama","state":"Osaka Prefecture","ISO3166-2-lvl4":"JP-27","country":"Japan","country_code":"jp"},"boundingbox":["34.4665040","34.5294220","135.5326370","135.5667733"]}]