[{"place_id":85038638,"licence":"Data © OpenStreetMap contributors, ODbL 1.0. http://osm.org/copyright","osm_type":"relation","osm_id":1431870,"lat":"47.8707939","lon":"21.1141032","category":"boundary","type":"administrative","place_rank":16,"importance":0.41842061779260414,"addresstype":"town","name":"Polgár","display_name":"Polgár, Hajdúnánási járás, Hajdú-Bihar, North Great Plain, Great Plain and North, 4090, Hungary","address":{"town":"Polgár","municipality":"Hajdúnánási járás","county":"Hajdú-Bihar","ISO3166-2-lvl6":"HU-HB","region":"North Great Plain","postcode":"4090","country":"Hungary","country_code":"hu"},"boundingbox":["47.8166412","47.9276880","21.0520206","21.2665157"]}]