[{"place_id":105386267,"licence":"Data © OpenStreetMap contributors, ODbL 1.0. http://osm.org/copyright","osm_type":"node","osm_id":240076912,"lat":"48.3902896","lon":"9.1845628","category":"place","type":"village","place_rank":19,"importance":0.3832672461146192,"addresstype":"village","name":"Undingen","display_name":"Undingen, Sonnenbühl, Landkreis Reutlingen, Baden-Württemberg, 72820, Germany","address":{"village":"Undingen","county":"Landkreis Reutlingen","state":"Baden-Württemberg","ISO3166-2-lvl4":"DE-BW","postcode":"72820","country":"Germany","country_code":"de"},"boundingbox":["48.3702896","48.4102896","9.1645628","9.2045628"]}]