[{"place_id":326875774,"licence":"Data © OpenStreetMap contributors, ODbL 1.0. http://osm.org/copyright","osm_type":"relation","osm_id":8195769,"lat":"45.7110618","lon":"-91.8065608","category":"boundary","type":"administrative","place_rank":14,"importance":0.27453211150644174,"addresstype":"village","name":"Town of Sarona","display_name":"Town of Sarona, Washburn County, Wisconsin, United States","address":{"village":"Town of Sarona","county":"Washburn County","state":"Wisconsin","ISO3166-2-lvl4":"US-WI","country":"United States","country_code":"us"},"boundingbox":["45.6388630","45.7245824","-91.9087975","-91.7854463"]}]