[{"place_id":299825274,"licence":"Data © OpenStreetMap contributors, ODbL 1.0. http://osm.org/copyright","osm_type":"relation","osm_id":119908,"lat":"33.1823419","lon":"-84.3615902","category":"boundary","type":"administrative","place_rank":16,"importance":0.33648735481596276,"addresstype":"village","name":"Williamson","display_name":"Williamson, Pike County, Georgia, United States","address":{"village":"Williamson","county":"Pike County","state":"Georgia","ISO3166-2-lvl4":"US-GA","country":"United States","country_code":"us"},"boundingbox":["33.1683530","33.1885270","-84.3708960","-84.3511410"]}]