[{"place_id":270379621,"licence":"Data © OpenStreetMap contributors, ODbL 1.0. http://osm.org/copyright","osm_type":"node","osm_id":458606354,"lat":"15.8337711","lon":"-96.3214401","category":"place","type":"town","place_rank":18,"importance":0.30000999999999994,"addresstype":"town","name":"Santa María Huatulco","display_name":"Santa María Huatulco, Oaxaca, Mexico","address":{"town":"Santa María Huatulco","county":"Santa María Huatulco","state":"Oaxaca","ISO3166-2-lvl4":"MX-OAX","country":"Mexico","country_code":"mx"},"boundingbox":["15.7937711","15.8737711","-96.3614401","-96.2814401"]}]