[{"place_id":173420094,"licence":"Data © OpenStreetMap contributors, ODbL 1.0. http://osm.org/copyright","osm_type":"node","osm_id":26701172,"lat":"52.7538673","lon":"0.3954774","category":"place","type":"town","place_rank":18,"importance":0.4901604254542792,"addresstype":"town","name":"King's Lynn","display_name":"King's Lynn, King's Lynn and West Norfolk, Norfolk, England, PE30 1BJ, United Kingdom","address":{"town":"King's Lynn","city":"King's Lynn and West Norfolk","county":"Norfolk","ISO3166-2-lvl6":"GB-NFK","state":"England","ISO3166-2-lvl4":"GB-ENG","postcode":"PE30 1BJ","country":"United Kingdom","country_code":"gb"},"boundingbox":["52.7138673","52.7938673","0.3554774","0.4354774"]}]