[{"place_id":274815386,"licence":"Data © OpenStreetMap contributors, ODbL 1.0. http://osm.org/copyright","osm_type":"relation","osm_id":76962,"lat":"51.5683589","lon":"-1.2373638","category":"boundary","type":"administrative","place_rank":20,"importance":0.34224222283715366,"addresstype":"village","name":"Blewbury","display_name":"Blewbury, Vale of White Horse, Oxfordshire, England, United Kingdom","address":{"village":"Blewbury","city":"Vale of White Horse","county":"Oxfordshire","ISO3166-2-lvl6":"GB-OXF","state":"England","ISO3166-2-lvl4":"GB-ENG","country":"United Kingdom","country_code":"gb"},"boundingbox":["51.5346123","51.5921949","-1.2865546","-1.2022103"]}]