[{"place_id":146795440,"licence":"Data © OpenStreetMap contributors, ODbL 1.0. http://osm.org/copyright","osm_type":"node","osm_id":97918380,"lat":"57.1691268","lon":"15.3525029","category":"place","type":"town","place_rank":18,"importance":0.3494483654395652,"addresstype":"town","name":"Åseda","display_name":"Åseda, Uppvidinge kommun, Kronoberg County, 360 70, Sweden","address":{"town":"Åseda","municipality":"Uppvidinge kommun","county":"Kronoberg County","ISO3166-2-lvl4":"SE-G","postcode":"360 70","country":"Sweden","country_code":"se"},"boundingbox":["57.1291268","57.2091268","15.3125029","15.3925029"]}]