[{"place_id":31337620,"licence":"Data © OpenStreetMap contributors, ODbL 1.0. http://osm.org/copyright","osm_type":"relation","osm_id":7905461,"lat":"50.504853","lon":"-116.0302062","category":"boundary","type":"administrative","place_rank":16,"importance":0.325302870611459,"addresstype":"village","name":"Invermere","display_name":"Invermere, Regional District of East Kootenay, British Columbia, Canada","address":{"village":"Invermere","county":"Regional District of East Kootenay","state":"British Columbia","ISO3166-2-lvl4":"CA-BC","country":"Canada","country_code":"ca"},"boundingbox":["50.4730783","50.5295017","-116.0551237","-116.0162888"]}]