[{"place_id":149757958,"licence":"Data © OpenStreetMap contributors, ODbL 1.0. http://osm.org/copyright","osm_type":"node","osm_id":392091506,"lat":"60.9010382","lon":"25.4704638","category":"place","type":"village","place_rank":19,"importance":0.27501,"addresstype":"village","name":"Herrala","display_name":"Herrala, Hollola, Lahti sub-region, Päijät-Häme, Southern Finland, Mainland Finland, 16500, Finland","address":{"village":"Herrala","town":"Hollola","municipality":"Lahti sub-region","county":"Päijät-Häme","ISO3166-2-lvl6":"FI-16","state_district":"Southern Finland","region":"Mainland Finland","postcode":"16500","country":"Finland","country_code":"fi"},"boundingbox":["60.8810382","60.9210382","25.4504638","25.4904638"]},{"place_id":149490711,"licence":"Data © OpenStreetMap contributors, ODbL 1.0. http://osm.org/copyright","osm_type":"node","osm_id":35500635,"lat":"60.3834563","lon":"25.2829874","category":"place","type":"village","place_rank":19,"importance":0.27501,"addresstype":"village","name":"Herrala","display_name":"Herrala, Sipoo, Helsinki sub-region, Uusimaa, Southern Finland, Mainland Finland, 04130, Finland","address":{"village":"Herrala","town":"Sipoo","municipality":"Helsinki sub-region","county":"Uusimaa","ISO3166-2-lvl6":"FI-18","state_district":"Southern Finland","region":"Mainland Finland","postcode":"04130","country":"Finland","country_code":"fi"},"boundingbox":["60.3634563","60.4034563","25.2629874","25.3029874"]},{"place_id":147275188,"licence":"Data © OpenStreetMap contributors, ODbL 1.0. http://osm.org/copyright","osm_type":"node","osm_id":6961575643,"lat":"60.5173185","lon":"23.9431372","category":"place","type":"hamlet","place_rank":20,"importance":0.25000999999999995,"addresstype":"hamlet","name":"Herrala","display_name":"Herrala, Nummi-Pusula, Lohja, Helsinki sub-region, Uusimaa, Southern Finland, Mainland Finland, Finland","address":{"hamlet":"Herrala","city_district":"Nummi-Pusula","city":"Lohja","municipality":"Helsinki sub-region","county":"Uusimaa","ISO3166-2-lvl6":"FI-18","state_district":"Southern Finland","region":"Mainland Finland","country":"Finland","country_code":"fi"},"boundingbox":["60.4973185","60.5373185","23.9231372","23.9631372"]},{"place_id":150020775,"licence":"Data © OpenStreetMap contributors, ODbL 1.0. http://osm.org/copyright","osm_type":"way","osm_id":635320921,"lat":"62.71146505","lon":"30.78456192522881","category":"landuse","type":"farmyard","place_rank":22,"importance":0.2000099999999999,"addresstype":"farmyard","name":"Herrala","display_name":"Herrala, Ilomantsi, Joensuu sub-region, North Karelia, Regional State Administrative Agency for Eastern Finland, Mainland Finland, Finland","address":{"farmyard":"Herrala","town":"Ilomantsi","municipality":"Joensuu sub-region","county":"North Karelia","ISO3166-2-lvl6":"FI-13","state_district":"Regional State Administrative Agency for Eastern Finland","region":"Mainland Finland","country":"Finland","country_code":"fi"},"boundingbox":["62.7109985","62.7119697","30.7834554","30.7857000"]},{"place_id":372696898,"licence":"Data © OpenStreetMap contributors, ODbL 1.0. http://osm.org/copyright","osm_type":"way","osm_id":1222785218,"lat":"61.2146159","lon":"22.056512365404814","category":"landuse","type":"farmyard","place_rank":22,"importance":0.2000099999999999,"addresstype":"farmyard","name":"Herrala","display_name":"Herrala, Köylypolvi, Kiukainen, Eura, Rauma sub-region, Satakunta, South-Western Finland, Mainland Finland, Finland","address":{"farmyard":"Herrala","suburb":"Köylypolvi","city_district":"Kiukainen","town":"Eura","municipality":"Rauma sub-region","county":"Satakunta","ISO3166-2-lvl6":"FI-17","state_district":"South-Western Finland","region":"Mainland Finland","country":"Finland","country_code":"fi"},"boundingbox":["61.2140358","61.2149610","22.0544514","22.0581235"]}]