[{"place_id":173994285,"licence":"Data © OpenStreetMap contributors, ODbL 1.0. http://osm.org/copyright","osm_type":"node","osm_id":166863567,"lat":"53.5745558","lon":"0.1099185","category":"place","type":"hamlet","place_rank":20,"importance":0.25000999999999995,"addresstype":"hamlet","name":"Spurn Head","display_name":"Spurn Head, Easington, East Riding of Yorkshire, England, United Kingdom","address":{"hamlet":"Spurn Head","suburb":"Easington","county":"East Riding of Yorkshire","ISO3166-2-lvl6":"GB-ERY","state":"England","ISO3166-2-lvl4":"GB-ENG","country":"United Kingdom","country_code":"gb"},"boundingbox":["53.5545558","53.5945558","0.0899185","0.1299185"]}]