[{"place_id":309226005,"licence":"Data © OpenStreetMap contributors, ODbL 1.0. http://osm.org/copyright","osm_type":"node","osm_id":150937404,"lat":"32.8528287","lon":"-116.6158525","category":"place","type":"hamlet","place_rank":20,"importance":0.36754970379538976,"addresstype":"hamlet","name":"Descanso","display_name":"Descanso, San Diego County, California, 91916, United States","address":{"hamlet":"Descanso","county":"San Diego County","state":"California","ISO3166-2-lvl4":"US-CA","postcode":"91916","country":"United States","country_code":"us"},"boundingbox":["32.8328287","32.8728287","-116.6358525","-116.5958525"]},{"place_id":376788289,"licence":"Data © OpenStreetMap contributors, ODbL 1.0. http://osm.org/copyright","osm_type":"relation","osm_id":16835985,"lat":"32.864564900000005","lon":"-116.63011931358452","category":"boundary","type":"census","place_rank":25,"importance":0.36754970379538976,"addresstype":"census","name":"Descanso","display_name":"Descanso, San Diego County, California, 91916, United States","address":{"census":"Descanso","county":"San Diego County","state":"California","ISO3166-2-lvl4":"US-CA","postcode":"91916","country":"United States","country_code":"us"},"boundingbox":["32.8272900","32.9023020","-116.6686165","-116.5748023"]}]