[{"place_id":102478241,"licence":"Data © OpenStreetMap contributors, ODbL 1.0. http://osm.org/copyright","osm_type":"relation","osm_id":2573978,"lat":"43.4257717","lon":"11.6084491","category":"waterway","type":"stream","place_rank":21,"importance":0.22500999999999993,"addresstype":"stream","name":"Ambra","display_name":"Ambra, Arezzo, Tuscany, Italy","address":{"stream":"Ambra","county":"Arezzo","ISO3166-2-lvl6":"IT-AR","state":"Tuscany","ISO3166-2-lvl4":"IT-52","country":"Italy","country_code":"it"},"boundingbox":["43.3700079","43.5248608","11.5056668","11.6287716"]},{"place_id":102127755,"licence":"Data © OpenStreetMap contributors, ODbL 1.0. http://osm.org/copyright","osm_type":"node","osm_id":252470476,"lat":"43.4161798","lon":"11.6032145","category":"place","type":"village","place_rank":19,"importance":0.1626514353057295,"addresstype":"village","name":"Ambra","display_name":"Ambra, Bucine, Arezzo, Tuscany, 52021, Italy","address":{"village":"Ambra","county":"Arezzo","ISO3166-2-lvl6":"IT-AR","state":"Tuscany","ISO3166-2-lvl4":"IT-52","postcode":"52021","country":"Italy","country_code":"it"},"boundingbox":["43.3961798","43.4361798","11.5832145","11.6232145"]}]