[{"place_id":296757945,"licence":"Data © OpenStreetMap contributors, ODbL 1.0. http://osm.org/copyright","osm_type":"node","osm_id":356581707,"lat":"37.1481912","lon":"-80.1053173","category":"natural","type":"peak","place_rank":18,"importance":0.30000999999999994,"addresstype":"peak","name":"Bent Mountain","display_name":"Bent Mountain, Franklin County, Virginia, 24059, United States","address":{"peak":"Bent Mountain","county":"Franklin County","state":"Virginia","ISO3166-2-lvl4":"US-VA","postcode":"24059","country":"United States","country_code":"us"},"boundingbox":["37.1481412","37.1482412","-80.1053673","-80.1052673"]},{"place_id":294925542,"licence":"Data © OpenStreetMap contributors, ODbL 1.0. http://osm.org/copyright","osm_type":"node","osm_id":154287727,"lat":"37.1412465","lon":"-80.1192065","category":"place","type":"hamlet","place_rank":20,"importance":0.2075345213990273,"addresstype":"hamlet","name":"Bent Mountain","display_name":"Bent Mountain, Roanoke County, Virginia, 24059, United States","address":{"hamlet":"Bent Mountain","county":"Roanoke County","state":"Virginia","ISO3166-2-lvl4":"US-VA","postcode":"24059","country":"United States","country_code":"us"},"boundingbox":["37.1212465","37.1612465","-80.1392065","-80.0992065"]}]