[{"place_id":248685290,"licence":"Data © OpenStreetMap contributors, ODbL 1.0. http://osm.org/copyright","osm_type":"node","osm_id":52251417,"lat":"51.6797696","lon":"-9.4523603","category":"place","type":"town","place_rank":18,"importance":0.42205899598756935,"addresstype":"town","name":"Bantry","display_name":"Bantry, West Cork, County Cork, Munster, P75 W242, Ireland","address":{"town":"Bantry","region":"West Cork","county":"County Cork","ISO3166-2-lvl6":"IE-CO","ISO3166-2-lvl5":"IE-M","postcode":"P75 W242","country":"Ireland","country_code":"ie"},"boundingbox":["51.6397696","51.7197696","-9.4923603","-9.4123603"]}]