[{"place_id":272282472,"licence":"Data © OpenStreetMap contributors, ODbL 1.0. http://osm.org/copyright","osm_type":"node","osm_id":3854743160,"lat":"53.5002551","lon":"-2.1852056","category":"place","type":"suburb","place_rank":19,"importance":0.27501,"addresstype":"suburb","name":"Newton Heath","display_name":"Newton Heath, Manchester, Greater Manchester, England, M40 2FP, United Kingdom","address":{"suburb":"Newton Heath","city":"Manchester","ISO3166-2-lvl8":"GB-MAN","state_district":"Greater Manchester","state":"England","ISO3166-2-lvl4":"GB-ENG","postcode":"M40 2FP","country":"United Kingdom","country_code":"gb"},"boundingbox":["53.4802551","53.5202551","-2.2052056","-2.1652056"]}]