[{"place_id":274302222,"licence":"Data © OpenStreetMap contributors, ODbL 1.0. http://osm.org/copyright","osm_type":"relation","osm_id":5365364,"lat":"20.41853305","lon":"-97.17882147109196","category":"boundary","type":"administrative","place_rank":16,"importance":0.35000999999999993,"addresstype":"city_district","name":"Álamo","display_name":"Álamo, Terrenos de la Ex-hacienda de Mazacapa, Gutiérrez Zamora, Veracruz, Mexico","address":{"city_district":"Álamo","municipality":"Terrenos de la Ex-hacienda de Mazacapa","county":"Gutiérrez Zamora","state":"Veracruz","ISO3166-2-lvl4":"MX-VER","country":"Mexico","country_code":"mx"},"boundingbox":["20.4140800","20.4256726","-97.1912986","-97.1764298"]},{"place_id":273067426,"licence":"Data © OpenStreetMap contributors, ODbL 1.0. http://osm.org/copyright","osm_type":"node","osm_id":472257748,"lat":"20.916667","lon":"-97.675","category":"place","type":"town","place_rank":18,"importance":0.30000999999999994,"addresstype":"town","name":"Álamo","display_name":"Álamo, Terrenos del Lote \"Álamo\", Álamo Temapache, Veracruz, 92730, Mexico","address":{"town":"Álamo","municipality":"Terrenos del Lote \"Álamo\"","county":"Álamo Temapache","state":"Veracruz","ISO3166-2-lvl4":"MX-VER","postcode":"92730","country":"Mexico","country_code":"mx"},"boundingbox":["20.8766670","20.9566670","-97.7150000","-97.6350000"]},{"place_id":273817118,"licence":"Data © OpenStreetMap contributors, ODbL 1.0. http://osm.org/copyright","osm_type":"relation","osm_id":4607014,"lat":"20.33222","lon":"-97.28444","category":"boundary","type":"administrative","place_rank":18,"importance":0.30000999999999994,"addresstype":"hamlet","name":"Álamo","display_name":"Álamo, Terrenos de la Ex- hacienda \"Río Claro\", Papantla, Veracruz, Mexico","address":{"hamlet":"Álamo","municipality":"Terrenos de la Ex- hacienda \"Río Claro\"","county":"Papantla","state":"Veracruz","ISO3166-2-lvl4":"MX-VER","country":"Mexico","country_code":"mx"},"boundingbox":["20.3302667","20.3337789","-97.2851790","-97.2819712"]},{"place_id":274099738,"licence":"Data © OpenStreetMap contributors, ODbL 1.0. http://osm.org/copyright","osm_type":"relation","osm_id":5729214,"lat":"20.867075","lon":"-97.67676467239212","category":"boundary","type":"administrative","place_rank":14,"importance":0.40001,"addresstype":"municipality","name":"Terrenos del Lote \"Álamo\"","display_name":"Terrenos del Lote \"Álamo\", Álamo Temapache, Veracruz, 92730, Mexico","address":{"municipality":"Terrenos del Lote \"Álamo\"","county":"Álamo Temapache","state":"Veracruz","ISO3166-2-lvl4":"MX-VER","postcode":"92730","country":"Mexico","country_code":"mx"},"boundingbox":["20.8061735","20.9274580","-97.7015001","-97.6623934"]}]