[{"place_id":16708506,"licence":"Data © OpenStreetMap contributors, ODbL 1.0. http://osm.org/copyright","osm_type":"relation","osm_id":6814224,"lat":"-34.873801","lon":"138.9599686","category":"boundary","type":"administrative","place_rank":18,"importance":0.3036784669331538,"addresstype":"town","name":"Mount Torrens","display_name":"Mount Torrens, Adelaide Hills Council, South Australia, 5244, Australia","address":{"town":"Mount Torrens","municipality":"Adelaide Hills Council","state":"South Australia","ISO3166-2-lvl4":"AU-SA","postcode":"5244","country":"Australia","country_code":"au"},"boundingbox":["-34.9223162","-34.8377986","138.9060909","139.0253961"]}]