[{"place_id":251816020,"licence":"Data © OpenStreetMap contributors, ODbL 1.0. http://osm.org/copyright","osm_type":"relation","osm_id":1279486,"lat":"44.9560756","lon":"-0.2104434","category":"boundary","type":"administrative","place_rank":16,"importance":0.5376938322692275,"addresstype":"village","name":"Lalande-de-Pomerol","display_name":"Lalande-de-Pomerol, Libourne, Gironde, Nouvelle-Aquitaine, Metropolitan France, 33500, France","address":{"village":"Lalande-de-Pomerol","municipality":"Libourne","county":"Gironde","ISO3166-2-lvl6":"FR-33","state":"Nouvelle-Aquitaine","ISO3166-2-lvl4":"FR-NAQ","region":"Metropolitan France","postcode":"33500","country":"France","country_code":"fr"},"boundingbox":["44.9411448","44.9693623","-0.2316941","-0.1756455"]}]