[{"place_id":76209831,"licence":"Data © OpenStreetMap contributors, ODbL 1.0. http://osm.org/copyright","osm_type":"relation","osm_id":3338488,"lat":"46.82092","lon":"4.96247","category":"boundary","type":"administrative","place_rank":16,"importance":0.5246756511039582,"addresstype":"village","name":"Bey","display_name":"Bey, Chalon-sur-Saône, Saône-et-Loire, Bourgogne-Franche-Comté, Metropolitan France, 71620, France","address":{"village":"Bey","municipality":"Chalon-sur-Saône","county":"Saône-et-Loire","ISO3166-2-lvl6":"FR-71","state":"Bourgogne-Franche-Comté","ISO3166-2-lvl4":"FR-BFC","region":"Metropolitan France","postcode":"71620","country":"France","country_code":"fr"},"boundingbox":["46.7993804","46.8447228","4.9473607","4.9913129"]}]