[{"place_id":68193248,"licence":"Data © OpenStreetMap contributors, ODbL 1.0. http://osm.org/copyright","osm_type":"relation","osm_id":2383547,"lat":"42.27414","lon":"9.479","category":"boundary","type":"administrative","place_rank":16,"importance":0.49836590084521587,"addresstype":"village","name":"Canale-di-Verde","display_name":"Canale-di-Verde, Corte, Haute-Corse, Corsica, Metropolitan France, 20230, France","address":{"village":"Canale-di-Verde","municipality":"Corte","county":"Haute-Corse","ISO3166-2-lvl6":"FR-2B","state":"Corsica","ISO3166-2-lvl4":"FR-20R","region":"Metropolitan France","postcode":"20230","country":"France","country_code":"fr"},"boundingbox":["42.2412230","42.2854840","9.4442125","9.5553052"]}]