[{"place_id":147866061,"licence":"Data © OpenStreetMap contributors, ODbL 1.0. http://osm.org/copyright","osm_type":"relation","osm_id":437275,"lat":"50.1361194","lon":"14.9859741","category":"boundary","type":"administrative","place_rank":16,"importance":0.4446472173275141,"addresstype":"town","name":"Sadská","display_name":"Sadská, okres Nymburk, Central Bohemia, 289 12, Czechia","address":{"town":"Sadská","municipality":"okres Nymburk","ISO3166-2-lvl7":"CZ-208","state":"Central Bohemia","postcode":"289 12","country":"Czechia","country_code":"cz"},"boundingbox":["50.1185026","50.1633617","14.9310182","15.0115242"]},{"place_id":147493642,"licence":"Data © OpenStreetMap contributors, ODbL 1.0. http://osm.org/copyright","osm_type":"relation","osm_id":429221,"lat":"50.14091765","lon":"14.975151141979051","category":"boundary","type":"administrative","place_rank":20,"importance":0.25000999999999995,"addresstype":"suburb","name":"Sadská","display_name":"Sadská, okres Nymburk, Central Bohemia, 289 12, Czechia","address":{"suburb":"Sadská","town":"Sadská","municipality":"okres Nymburk","ISO3166-2-lvl7":"CZ-208","state":"Central Bohemia","postcode":"289 12","country":"Czechia","country_code":"cz"},"boundingbox":["50.1185026","50.1633617","14.9310182","15.0115242"]}]